Swarm/__init__.py
Swarm/bots.py
Swarm/game.py
Swarm/main.py
Swarm/sim.py
Swarm-0.0.2.dist-info/LICENSE
Swarm-0.0.2.dist-info/METADATA
Swarm-0.0.2.dist-info/WHEEL
Swarm-0.0.2.dist-info/top_level.txt
Swarm-0.0.2.dist-info/RECORD
