Metadata-Version: 2.1
Name: Swarm
Version: 0.0.2
Summary: Swarm is a strategy rouge-like space simulator game written with `pygame/python3`.
Home-page: https://github.com/Wykleph/Swarm
Author: py-am-i
Author-email: duckpuncherirl@gmail.com
License: UNKNOWN
Platform: UNKNOWN
Classifier: Programming Language :: Python :: 3
Classifier: License :: OSI Approved :: MIT License
Classifier: Operating System :: OS Independent
